gcs_logger/__init__.py
gcs_logger/enums.py
gcs_logger/main.py
gcs_logger-0.1.7.dist-info/LICENSE
gcs_logger-0.1.7.dist-info/METADATA
gcs_logger-0.1.7.dist-info/WHEEL
gcs_logger-0.1.7.dist-info/RECORD
