Metadata-Version: 2.1
Name: gcs-logger
Version: 0.1.7
Summary: Logging tool for GameChange Solar projects
License: MIT
Author: GameChangeSolar Software Team
Author-email: software@gamechangesolar.com
Maintainer: David Aviles
Maintainer-email: david.aviles@gamechangesolar.com
Requires-Python: >=3.10,<4
Classifier: License :: OSI Approved :: MIT License
Classifier: Programming Language :: Python :: 3
Classifier: Programming Language :: Python :: 3.10
Classifier: Programming Language :: Python :: 3.11
Classifier: Programming Language :: Python :: 3.12
Classifier: Programming Language :: Python :: 3.13
